{"0": {"sum_reward": 1, "duration": 11542}, "1": {"sum_reward": 1, "duration": 3540}, "2": {"sum_reward": 1, "duration": 4414}, "3": {"sum_reward": 1, "duration": 1425}, "4": {"sum_reward": 1, "duration": 471}, "5": {"sum_reward": 1, "duration": 123}, "6": {"sum_reward": 1, "duration": 1216}, "7": {"sum_reward": 1, "duration": 5393}, "8": {"sum_reward": 1, "duration": 1255}, "9": {"sum_reward": 1, "duration": 820}, "10": {"sum_reward": 1, "duration": 992}, "11": {"sum_reward": 1, "duration": 886}, "12": {"sum_reward": 1, "duration": 2053}, "13": {"sum_reward": 1, "duration": 1463}, "14": {"sum_reward": 1, "duration": 1507}, "15": {"sum_reward": 1, "duration": 6267}, "16": {"sum_reward": 1, "duration": 9044}, "17": {"sum_reward": 1, "duration": 190}, "18": {"sum_reward": 1, "duration": 5736}, "19": {"sum_reward": 1, "duration": 5704}, "20": {"sum_reward": 1, "duration": 5947}, "21": {"sum_reward": 1, "duration": 2141}, "22": {"sum_reward": 1, "duration": 2176}, "23": {"sum_reward": 1, "duration": 2849}, "24": {"sum_reward": 1, "duration": 3799}, "25": {"sum_reward": 1, "duration": 1166}, "26": {"sum_reward": 1, "duration": 5689}, "27": {"sum_reward": 1, "duration": 4517}, "28": {"sum_reward": 1, "duration": 141}, "29": {"sum_reward": 1, "duration": 5639}, "30": {"sum_reward": 1, "duration": 1443}, "31": {"sum_reward": 1, "duration": 805}}