{"0": {"sum_reward": 1, "duration": 873}, "1": {"sum_reward": 1, "duration": 2547}, "2": {"sum_reward": 1, "duration": 208}, "3": {"sum_reward": 1, "duration": 1624}, "4": {"sum_reward": 1, "duration": 1062}, "5": {"sum_reward": 1, "duration": 2084}, "6": {"sum_reward": 1, "duration": 319}, "7": {"sum_reward": 1, "duration": 226}, "8": {"sum_reward": 1, "duration": 1243}, "9": {"sum_reward": 1, "duration": 1679}, "10": {"sum_reward": 1, "duration": 780}, "11": {"sum_reward": 1, "duration": 82}, "12": {"sum_reward": 1, "duration": 480}, "13": {"sum_reward": 1, "duration": 1227}, "14": {"sum_reward": 1, "duration": 382}, "15": {"sum_reward": 1, "duration": 232}, "16": {"sum_reward": 1, "duration": 745}, "17": {"sum_reward": 1, "duration": 1201}, "18": {"sum_reward": 1, "duration": 829}, "19": {"sum_reward": 1, "duration": 393}, "20": {"sum_reward": 1, "duration": 85}, "21": {"sum_reward": 1, "duration": 124}, "22": {"sum_reward": 1, "duration": 1821}, "23": {"sum_reward": 1, "duration": 371}, "24": {"sum_reward": 1, "duration": 121}, "25": {"sum_reward": 1, "duration": 1103}, "26": {"sum_reward": 1, "duration": 608}, "27": {"sum_reward": 1, "duration": 668}, "28": {"sum_reward": 1, "duration": 1823}, "29": {"sum_reward": 1, "duration": 786}, "30": {"sum_reward": 1, "duration": 871}, "31": {"sum_reward": 1, "duration": 207}, "32": {"sum_reward": 1, "duration": 390}, "33": {"sum_reward": 1, "duration": 540}, "34": {"sum_reward": 1, "duration": 361}, "35": {"sum_reward": 1, "duration": 293}, "36": {"sum_reward": 1, "duration": 143}, "37": {"sum_reward": 1, "duration": 67}, "38": {"sum_reward": 1, "duration": 349}, "39": {"sum_reward": 1, "duration": 105}, "40": {"sum_reward": 1, "duration": 344}, "41": {"sum_reward": 1, "duration": 56}, "42": {"sum_reward": 1, "duration": 4604}, "43": {"sum_reward": 1, "duration": 1913}, "44": {"sum_reward": 1, "duration": 708}, "45": {"sum_reward": 1, "duration": 693}, "46": {"sum_reward": 1, "duration": 704}, "47": {"sum_reward": 1, "duration": 962}, "48": {"sum_reward": 1, "duration": 373}, "49": {"sum_reward": 1, "duration": 770}, "50": {"sum_reward": 1, "duration": 1131}, "51": {"sum_reward": 1, "duration": 428}, "52": {"sum_reward": 1, "duration": 1344}, "53": {"sum_reward": 1, "duration": 173}, "54": {"sum_reward": 1, "duration": 96}, "55": {"sum_reward": 1, "duration": 675}, "56": {"sum_reward": 1, "duration": 534}, "57": {"sum_reward": 1, "duration": 2174}, "58": {"sum_reward": 1, "duration": 659}, "59": {"sum_reward": 1, "duration": 914}, "60": {"sum_reward": 1, "duration": 710}, "61": {"sum_reward": 1, "duration": 621}, "62": {"sum_reward": 1, "duration": 649}, "63": {"sum_reward": 1, "duration": 726}, "64": {"sum_reward": 1, "duration": 77}, "65": {"sum_reward": 1, "duration": 1654}, "66": {"sum_reward": 1, "duration": 929}, "67": {"sum_reward": 1, "duration": 3046}, "68": {"sum_reward": 1, "duration": 1288}, "69": {"sum_reward": 1, "duration": 1020}, "70": {"sum_reward": 1, "duration": 1257}, "71": {"sum_reward": 1, "duration": 902}, "72": {"sum_reward": 1, "duration": 65}, "73": {"sum_reward": 1, "duration": 152}, "74": {"sum_reward": 1, "duration": 1255}, "75": {"sum_reward": 1, "duration": 767}, "76": {"sum_reward": 1, "duration": 472}, "77": {"sum_reward": 1, "duration": 955}, "78": {"sum_reward": 1, "duration": 359}, "79": {"sum_reward": 1, "duration": 372}, "80": {"sum_reward": 1, "duration": 1173}, "81": {"sum_reward": 1, "duration": 1000}, "82": {"sum_reward": 1, "duration": 380}, "83": {"sum_reward": 1, "duration": 844}, "84": {"sum_reward": 1, "duration": 351}, "85": {"sum_reward": 1, "duration": 1008}, "86": {"sum_reward": 1, "duration": 367}, "87": {"sum_reward": 1, "duration": 989}, "88": {"sum_reward": 1, "duration": 433}, "89": {"sum_reward": 1, "duration": 362}, "90": {"sum_reward": 1, "duration": 741}, "91": {"sum_reward": 1, "duration": 197}, "92": {"sum_reward": 1, "duration": 182}, "93": {"sum_reward": 1, "duration": 1229}, "94": {"sum_reward": 1, "duration": 430}, "95": {"sum_reward": 1, "duration": 116}, "96": {"sum_reward": 1, "duration": 618}, "97": {"sum_reward": 1, "duration": 464}, "98": {"sum_reward": 1, "duration": 713}, "99": {"sum_reward": 1, "duration": 132}, "100": {"sum_reward": 1, "duration": 1170}, "101": {"sum_reward": 1, "duration": 251}, "102": {"sum_reward": 1, "duration": 638}, "103": {"sum_reward": 1, "duration": 2981}, "104": {"sum_reward": 1, "duration": 681}, "105": {"sum_reward": 1, "duration": 1412}, "106": {"sum_reward": 1, "duration": 215}, "107": {"sum_reward": 1, "duration": 313}, "108": {"sum_reward": 1, "duration": 433}, "109": {"sum_reward": 1, "duration": 526}, "110": {"sum_reward": 1, "duration": 305}, "111": {"sum_reward": 1, "duration": 492}, "112": {"sum_reward": 1, "duration": 105}, "113": {"sum_reward": 1, "duration": 1244}, "114": {"sum_reward": 1, "duration": 645}, "115": {"sum_reward": 1, "duration": 571}, "116": {"sum_reward": 1, "duration": 246}, "117": {"sum_reward": 1, "duration": 1619}, "118": {"sum_reward": 1, "duration": 904}, "119": {"sum_reward": 1, "duration": 2023}, "120": {"sum_reward": 1, "duration": 1027}, "121": {"sum_reward": 1, "duration": 189}, "122": {"sum_reward": 1, "duration": 1205}, "123": {"sum_reward": 1, "duration": 233}, "124": {"sum_reward": 1, "duration": 161}, "125": {"sum_reward": 1, "duration": 1413}, "126": {"sum_reward": 1, "duration": 584}, "127": {"sum_reward": 1, "duration": 960}, "128": {"sum_reward": 1, "duration": 114}, "129": {"sum_reward": 1, "duration": 632}}